wagner_dio_image_processing/__init__.py
wagner_dio_image_processing/processing/__init__.py
wagner_dio_image_processing/processing/combination.py
wagner_dio_image_processing/processing/transformation.py
wagner_dio_image_processing/utils/__init__.py
wagner_dio_image_processing/utils/io.py
wagner_dio_image_processing/utils/plot.py
wagner_dio_image_processing-0.0.1.dist-info/METADATA
wagner_dio_image_processing-0.0.1.dist-info/WHEEL
wagner_dio_image_processing-0.0.1.dist-info/top_level.txt
wagner_dio_image_processing-0.0.1.dist-info/RECORD
