Metadata-Version: 2.1
Name: wagner-dio-image-processing
Version: 0.0.1
Summary: image processing python project example
Home-page: https://github.com/wagnerdtrindade/image-processing-package
Author: wagner trindade
Author-email: wagner.d.trindade@gmail.com
License: UNKNOWN
Platform: UNKNOWN
Requires-Python: >=3.8
Requires-Dist: matplotlib
Requires-Dist: numpy
Requires-Dist: scikit-image (>=0.16.1)
